txsocksx/__init__.py
txsocksx/_version.py
txsocksx/client.py
txsocksx/constants.py
txsocksx/errors.py
txsocksx/grammar.py
txsocksx/http.py
txsocksx/ssl.py
txsocksx/tls.py
txsocksx/test/__init__.py
txsocksx/test/test_client.py
txsocksx/test/test_grammar.py
txsocksx/test/test_http.py
txsocksx/test/test_tls.py
txsocksx/test/util.py
txsocksx-1.15.0.2.dist-info/DESCRIPTION.rst
txsocksx-1.15.0.2.dist-info/METADATA
txsocksx-1.15.0.2.dist-info/metadata.json
txsocksx-1.15.0.2.dist-info/RECORD
txsocksx-1.15.0.2.dist-info/top_level.txt
txsocksx-1.15.0.2.dist-info/WHEEL
