Metadata-Version: 2.0
Name: txsocksx
Version: 1.15.0.2
Summary: Twisted client endpoints for SOCKS{4,4a,5}
Home-page: https://github.com/habnabit/txsocksx
Author: Aaron Gallagher
Author-email: _@habnab.it
License: ISC
Platform: UNKNOWN
Classifier: Development Status :: 3 - Alpha
Classifier: Framework :: Twisted
Classifier: Intended Audience :: Developers
Classifier: License :: OSI Approved :: ISC License (ISCL)
Classifier: Operating System :: OS Independent
Classifier: Programming Language :: Python :: 2.6
Classifier: Programming Language :: Python :: 2.7
Classifier: Programming Language :: Python :: 2 :: Only
Classifier: Topic :: Internet
Requires-Dist: Twisted (>=10.1)
Requires-Dist: Parsley (>=1.2)
